xkcd1172/__init__.py
xkcd1172/main.py
xkcd1172-0.1.0.dist-info/LICENSE
xkcd1172-0.1.0.dist-info/METADATA
xkcd1172-0.1.0.dist-info/WHEEL
xkcd1172-0.1.0.dist-info/entry_points.txt
xkcd1172-0.1.0.dist-info/top_level.txt
xkcd1172-0.1.0.dist-info/RECORD
