Metadata-Version: 2.1
Name: xkcd1172
Version: 0.1.0
Summary: Rapidly increases CPU temperature when holding down the spacebar
Home-page: https://git.dawidpotocki.com/dawid/xkcd1172
Author: Dawid Potocki
Author-email: pypi@dawidpotocki.com
Classifier: Programming Language :: Python :: 3
Classifier: License :: OSI Approved :: BSD License
Classifier: Operating System :: POSIX
Classifier: Environment :: X11 Applications
Requires-Python: >=3.7
License-File: LICENSE
Requires-Dist: python-xlib (<1,>=0.31)
